coded_flows/__init__.py
coded_flows/types/__init__.py
coded_flows/types/extra.py
coded_flows/utils/__init__.py
coded_flows/utils/converters.py
coded_flows/utils/logging.py
coded_flows/utils/media.py
coded_flows/utils/miscellaneous.py
coded_flows-0.7.4.dist-info/METADATA
coded_flows-0.7.4.dist-info/WHEEL
coded_flows-0.7.4.dist-info/RECORD
