Metadata-Version: 2.4
Name: coded-flows
Version: 0.7.4
Summary: Various utilities for Coded Flows
Author: COLOR CODED CODES
Author-email: contact@colorcoded.codes
Requires-Python: >=3.10,<4.0
Classifier: Programming Language :: Python :: 3
Classifier: Programming Language :: Python :: 3.10
Classifier: Programming Language :: Python :: 3.11
Classifier: Programming Language :: Python :: 3.12
Classifier: Programming Language :: Python :: 3.13
Classifier: Programming Language :: Python :: 3.14
Requires-Dist: email-validator (>=2.0.0,<3.0.0)
Requires-Dist: pandas (>=2.1.0,<3.0.0)
Requires-Dist: pillow (==11.3.0)
Requires-Dist: polars (>=1.0.0,<2.0.0)
Requires-Dist: pyarrow (>=18.0.0,<19.0.0)
Requires-Dist: pycountry (>=24.6.1,<25.0.0)
Requires-Dist: pydantic-extra-types (>=2.6.0,<3.0.0)
Requires-Dist: pydantic[email] (>=2.6.4,<3.0.0)
